abeec/__init__.py
abeec/_version.py
abeec/sampler.py
abeec/utils.py
abeec-0.3.dist-info/LICENCE
abeec-0.3.dist-info/METADATA
abeec-0.3.dist-info/WHEEL
abeec-0.3.dist-info/top_level.txt
abeec-0.3.dist-info/RECORD
